komitto/__init__.py
komitto/config.py
komitto/editor.py
komitto/git_utils.py
komitto/i18n.py
komitto/learn.py
komitto/main.py
komitto/prompt.py
komitto/llm/__init__.py
komitto/llm/anthropic_client.py
komitto/llm/base.py
komitto/llm/factory.py
komitto/llm/gemini_client.py
komitto/llm/openai_client.py
komitto/locales/en.json
komitto/locales/ja.json
komitto/tui/__init__.py
komitto/tui/app.py
komitto/tui/styles.tcss
komitto-0.3.3.dist-info/licenses/LICENSE
komitto-0.3.3.dist-info/METADATA
komitto-0.3.3.dist-info/WHEEL
komitto-0.3.3.dist-info/entry_points.txt
komitto-0.3.3.dist-info/top_level.txt
komitto-0.3.3.dist-info/RECORD
