Metadata-Version: 2.4
Name: komitto
Version: 0.3.3
Summary: A CLI tool that generates semantic Japanese commit message prompts for LLMs from Git diff information.
Author: mxcake
License: MIT License
Project-URL: Homepage, https://github.com/mxcake3893/komitto
Classifier: Programming Language :: Python :: 3
Classifier: Operating System :: OS Independent
Classifier: License :: OSI Approved :: MIT License
Requires-Python: >=3.6
License-File: LICENSE
Requires-Dist: pyperclip
Requires-Dist: platformdirs
Requires-Dist: tomli
Requires-Dist: openai
Requires-Dist: google-genai
Requires-Dist: anthropic
Requires-Dist: rich
Requires-Dist: textual
Provides-Extra: dev
Requires-Dist: pytest; extra == "dev"
Dynamic: license-file
